napari_itk_io/__init__.py
napari_itk_io/_reader.py
napari_itk_io/_version.py
napari_itk_io/_writer.py
napari_itk_io/napari.yaml
napari_itk_io/_tests/__init__.py
napari_itk_io/_tests/test_reader.py
napari_itk_io/_tests/test_writer.py
napari_itk_io-0.4.1.dist-info/LICENSE
napari_itk_io-0.4.1.dist-info/METADATA
napari_itk_io-0.4.1.dist-info/WHEEL
napari_itk_io-0.4.1.dist-info/entry_points.txt
napari_itk_io-0.4.1.dist-info/top_level.txt
napari_itk_io-0.4.1.dist-info/RECORD
