Metadata-Version: 2.1
Name: napari-itk-io
Version: 0.4.1
Summary: File IO with itk for napari
Home-page: https://github.com/InsightSoftwareConsortium/napari-itk-io
Author: Matt McCormick
Author-email: matt.mccormick@kitware.com
License: Apache-2.0
Classifier: Development Status :: 4 - Beta
Classifier: Intended Audience :: Developers
Classifier: Framework :: napari
Classifier: Topic :: Software Development :: Testing
Classifier: Programming Language :: Python
Classifier: Programming Language :: Python :: 3
Classifier: Programming Language :: Python :: 3.9
Classifier: Programming Language :: Python :: 3.10
Classifier: Programming Language :: Python :: 3.11
Classifier: Programming Language :: Python :: 3.12
Classifier: Programming Language :: Python :: 3.13
Classifier: Operating System :: OS Independent
Classifier: License :: OSI Approved :: Apache Software License
Requires-Python: >=3.8
License-File: LICENSE
Requires-Dist: numpy
Requires-Dist: napari-plugin-engine>=0.2.0
Requires-Dist: itk-io>=5.2.0
Requires-Dist: itk-napari-conversion
